{
  "localization": "ko",
  "name": "dYdX Protocol (dYdX Protocol)",
  "symbol": "DYDX.dydx",
  "coingeckoID": "dydx-chain",
  "websiteURL": "https://dydx.trade/",
  "twitterURL": "https://twitter.com/dYdX",
  "description": "DYDX는 파생상품과 무기한 계약에 초점을 맞춘 분산형 거래 플랫폼으로, 중개자 없이 안전하고 효율적인 거래 경험을 제공합니다.<inlang-LineFeed>\nDYDX는 파생상품과 영구 계약을 전문으로 하는 선도적인 분산형 거래 플랫폼입니다. 이를 통해 사용자는 레버리지로 거래할 수 있으며, 중개자 없이 정교하고 효율적인 거래 환경을 제공합니다. Ethereum 블록체인을 기반으로 하는 DYDX는 스마트 계약을 사용하여 거래 보안과 투명성을 보장하고, 사용자는 자금과 거래에 대한 완전한 통제권을 갖습니다.<inlang-LineFeed>\nDYDX 플랫폼의 네이티브 토큰인 DYDX는 거버넌스, 스테이킹, 수수료 할인에 사용되어 적극적인 참여를 장려하는 생태계에 필수적입니다. DYDX는 광범위한 거래 쌍을 제공하고 마진 거래 및 대출과 같은 고급 거래 기능을 지원합니다. 분산형 금융의 이점과 기존 거래 플랫폼 기능을 결합하여 DYDX는 보다 개방적이고 포괄적인 금융 시스템을 위한 길을 개척하고 있습니다."
}