{
  "localization": "pl",
  "name": "Shitmos",
  "symbol": "SHITMOS",
  "websiteURL": "https://shitmos.wtf",
  "twitterURL": "https://twitter.com/shitoncosmos",
  "description": "Najwa\u017cniejszy memecoin nienawi\u015bci do samego siebie w Cosmos Network.<inlang-LineFeed>\nShitmos to uczciwie wprowadzony token wdra\u017cany za po\u015brednictwem protoko\u0142u \u0142adowania p\u0142ynno\u015bci start.cooking (LBP) w \u0142a\u0144cuchu blok\u00f3w Osmosis. Jest zasilany przez Stref\u0119 Ekonomiczn\u0105 Shitmos (SSE) i zosta\u0142 zaprojektowany w celu zjednoczenia sieci Cosmos Network i du\u017cych ekosystem\u00f3w mi\u0119dzy \u0142a\u0144cuchami poprzez sprawianie, \u017ce kryptowaluty b\u0119d\u0105 zabaw\u0105. SSE to federacja kolekcji nft w Stargaze, kt\u00f3ra wspiera Shitmos, przekazuj\u0105c co najmniej 2% tantiem na rzecz zakup\u00f3w Shitmos na otwartym rynku.",
  "base": "factory/osmo1q77cw0mmlluxu0wr29fcdd0tdnh78gzhkvhe4n6ulal9qvrtu43qtd0nh8/shitmos"
}
