{
  "localization": "gu",
  "name": "OmniFlix",
  "symbol": "FLIX",
  "coingeckoID": "omniflix-network",
  "websiteURL": "https://omniflix.network/",
  "twitterURL": "https://twitter.com/OmniFlixNetwork",
  "description": "OmniFlix એ વિકેન્દ્રિત મીડિયા પ્લેટફોર્મ છે જે સામગ્રી સર્જકોને બ્લોકચેન ટેક્નોલોજીનો ઉપયોગ કરીને તેમની ડિજિટલ સામગ્રીનું વિતરણ, મુદ્રીકરણ અને સંચાલન કરવા સક્ષમ બનાવે છે.<inlang-LineFeed>\nOmniFlix એ ડિજિટલ સામગ્રીના વિતરણ, મુદ્રીકરણ અને સંચાલન માટે સાધનો પ્રદાન કરીને સામગ્રી નિર્માતાઓને સશક્ત બનાવવા માટે રચાયેલ વિકેન્દ્રિત મીડિયા પ્લેટફોર્મ છે. બ્લોકચેન ટેક્નોલોજીનો લાભ લઈને, OmniFlix એ સુનિશ્ચિત કરે છે કે સર્જકો તેમના કાર્ય પર નિયંત્રણ જાળવી રાખે છે, તેમના પ્રેક્ષકો સાથે સીધી ક્રિયાપ્રતિક્રિયા અને પારદર્શક આવકના પ્રવાહોને મંજૂરી આપે છે. પ્લેટફોર્મ વિડિયો, ઑડિયો અને ટેક્સ્ટ સહિત વિવિધ મીડિયા પ્રકારોને સપોર્ટ કરે છે, જે સર્જકોને વિશાળ પ્રેક્ષકો સુધી પહોંચવામાં સક્ષમ બનાવે છે. OmniFlix ના મૂળ ટોકનનો ઉપયોગ વ્યવહારો, સ્ટેકિંગ અને ગવર્નન્સ માટે થાય છે, જે વપરાશકર્તાઓને પ્લેટફોર્મની ઇકોસિસ્ટમમાં ભાગ લેવા અને તેની વૃદ્ધિ અને વિકાસમાં યોગદાન આપવા માટે પ્રોત્સાહિત કરે છે. પ્લેટફોર્મનો ઉદ્દેશ્ય પરંપરાગત સામગ્રી વિતરણ મોડલ્સ માટે વિકેન્દ્રિત વિકલ્પ પ્રદાન કરીને મીડિયા ઉદ્યોગમાં ક્રાંતિ લાવવાનો છે."
}