{
  "localization": "pt-br",
  "name": "Lorenzo stBTC",
  "symbol": "stBTC",
  "websiteURL": "https://www.lorenzo-protocol.xyz/",
  "twitterURL": "https://x.com/LorenzoProtocol",
  "description": "stBTC \u00e9 o token principal l\u00edquido do protocolo Lorenzo, projetado para representar Bitcoin apostado dentro do ecossistema Babylon.<inlang-LineFeed><inlang-LineFeed><inlang-LineFeed>\nO stBTC serve como um componente crucial do protocolo Lorenzo, permitindo que os detentores de Bitcoin desbloqueiem a liquidez de seus ativos enquanto participam da seguran\u00e7a das redes Proof-of-Stake (PoS). Ao fazer staking de BTC por meio do Lorenzo, os usu\u00e1rios recebem stBTC, que \u00e9 resgat\u00e1vel 1 para 1 pelo Bitcoin original. Esse mecanismo permite que os usu\u00e1rios ganhem rendimento sem sacrificar a liquidez, pois o stBTC pode ser utilizado livremente dentro do ecossistema Lorenzo DeFi.<inlang-LineFeed>\nO inovador sistema de token duplo de stBTC e Yield Accruing Tokens (YATs) capacita os usu\u00e1rios n\u00e3o apenas a fazer stake de seus BTC, mas tamb\u00e9m a se envolver em v\u00e1rias atividades financeiras descentralizadas, como negocia\u00e7\u00e3o, empr\u00e9stimo e garantia. Isso aumenta a utilidade e a flexibilidade do Bitcoin, fornecendo oportunidades financeiras adicionais ao mesmo tempo em que contribui para a seguran\u00e7a das redes PoS.<inlang-LineFeed>\nO papel do stBTC no protocolo Lorenzo ilustra sua import\u00e2ncia na cria\u00e7\u00e3o de um ecossistema financeiro altamente interconectado e eficiente, tornando-o um ativo valioso no cen\u00e1rio mais amplo das finan\u00e7as descentralizadas.",
  "base": "ibc/453B5B25834A5D4B8FE1E894E69D73F46424F28E8ED3D8E8CA654AEFF1EC5D3B"
}
