{
  "localization": "es",
  "name": "Kujira",
  "symbol": "KUJI",
  "coingeckoID": "kujira",
  "websiteURL": "https://kujira.network/",
  "twitterURL": "https://twitter.com/TeamKujira",
  "description": "Kujira es una plataforma de finanzas descentralizadas (DeFi) que ofrece un conjunto de herramientas y servicios para gestionar y optimizar inversiones y activos digitales.<inlang-LineFeed>\nKujira proporciona una plataforma DeFi integral que incluye herramientas para otorgar pr\u00e9stamos, pedir prestado y generar rendimiento, aprovechando la tecnolog\u00eda blockchain para ofrecer una experiencia de usuario transparente, segura y eficiente. El token nativo, KUJI, es fundamental para el ecosistema y se utiliza para tarifas de transacci\u00f3n, apuestas y gobernanza. El dise\u00f1o centrado en el usuario y las caracter\u00edsticas innovadoras de Kujira lo convierten en una opci\u00f3n popular en el espacio DeFi, lo que permite a los usuarios maximizar sus retornos y administrar eficazmente sus activos digitales.",
  "base": "ibc/BB6BCDB515050BAE97516111873CCD7BCF1FD0CCB723CC12F3C4F704D6C646CE"
}
