{
  "localization": "de",
  "name": "Secret Network",
  "symbol": "SCRT",
  "coingeckoID": "secret",
  "websiteURL": "https://scrt.network/",
  "twitterURL": "https://twitter.com/SecretNetwork",
  "description": "Secret Network ist eine auf Datenschutz ausgerichtete Blockchain, die private und sichere Smart Contracts erm\u00f6glicht und sensible Daten sch\u00fctzt.<inlang-LineFeed>\nSecret Network ist eine Blockchain-Plattform, die sich auf Datenschutz und Sicherheit konzentriert, indem sie private Smart Contracts, sogenannte Secret Contracts, erm\u00f6glicht. Diese Vertr\u00e4ge erm\u00f6glichen es Entwicklern, dezentrale Anwendungen (dApps) zu erstellen, die vertrauliche Daten nutzen k\u00f6nnen, ohne sie auf der Blockchain offenzulegen. Durch die Einbindung datenschutzfreundlicher Technologien stellt Secret Network sicher, dass die Daten vertraulich bleiben, w\u00e4hrend gleichzeitig komplexe Berechnungen und Interaktionen m\u00f6glich sind. Der native Token SCRT wird f\u00fcr Transaktionsgeb\u00fchren, Staking und Governance verwendet und erm\u00f6glicht Benutzern die Teilnahme an den Vorg\u00e4ngen und Entscheidungsprozessen des Netzwerks. Secret Network zielt darauf ab, den Datenschutz und die Funktionalit\u00e4t von Blockchain-Anwendungen zu verbessern und es f\u00fcr Anwendungsf\u00e4lle geeignet zu machen, bei denen die Datenvertraulichkeit von gr\u00f6\u00dfter Bedeutung ist.",
  "base": "ibc/0954E1C28EB7AF5B72D24F3BC2B47BBB2FDF91BDDFD57B74B99E133AED40972A"
}
