{
  "localization": "en",
  "name": "Void",
  "symbol": "VOID",
  "description": {
    "en": "Void",
    "de": "Leere",
    "es": "Vac\u00edo",
    "fa": "\u062e\u0627\u0644\u06cc",
    "fr": "Vide",
    "gu": "\u0ab0\u0aa6\u0aac\u0abe\u0aa4\u0ab2",
    "hi": "\u0916\u093e\u0932\u0940\u092a\u0928",
    "ja": "\u7a7a\u6240",
    "ko": "\ubb34\ud6a8\uc758",
    "pl": "Pr\u00f3\u017cnia",
    "pt-br": "Vazio",
    "ro": "Vidul",
    "ru": "\u041f\u0443\u0441\u0442\u043e\u0442\u0430",
    "tr": "Ge\u00e7ersiz",
    "zh-cn": "\u7a7a\u767d",
    "zh-hk": "\u7a7a\u767d",
    "zh-tw": "\u7a7a\u767d"
  },
  "base": "ibc/593F820ECE676A3E0890C734EC4F3A8DE16EC10A54EEDFA8BDFEB40EEA903960"
}
