{
  "localization": "en",
  "name": "Kujira",
  "symbol": "KUJI",
  "coingeckoID": "kujira",
  "websiteURL": "https://kujira.network/",
  "twitterURL": "https://twitter.com/TeamKujira",
  "description": "Kujira is a decentralized finance (DeFi) platform offering a suite of tools and services for managing and optimizing digital assets and investments.\n\nKujira provides a comprehensive DeFi platform that includes tools for lending, borrowing, and yield farming, leveraging blockchain technology to offer a transparent, secure, and efficient user experience. The native token, KUJI, is central to the ecosystem, used for transaction fees, staking, and governance. Kujira's user-centric design and innovative features make it a popular choice in the DeFi space, enabling users to maximize their returns and effectively manage their digital assets.",
  "base": "ibc/BB6BCDB515050BAE97516111873CCD7BCF1FD0CCB723CC12F3C4F704D6C646CE"
}
