{
  "localization": "ja",
  "name": "BitCanna",
  "symbol": "BCNA",
  "coingeckoID": "bitcanna",
  "websiteURL": "http://www.bitcanna.io/",
  "twitterURL": "https://twitter.com/BitCannaGlobal",
  "description": "BCNA \u30b3\u30a4\u30f3\u306f BitCanna \u30cd\u30c3\u30c8\u30ef\u30fc\u30af\u5185\u306e\u30c8\u30e9\u30f3\u30b6\u30af\u30b7\u30e7\u30f3 \u30c8\u30fc\u30af\u30f3\u3067\u3042\u308a\u3001\u652f\u6255\u3044\u30cd\u30c3\u30c8\u30ef\u30fc\u30af\u3001\u30b5\u30d7\u30e9\u30a4 \u30c1\u30a7\u30fc\u30f3\u3001\u4fe1\u983c\u30cd\u30c3\u30c8\u30ef\u30fc\u30af\u3092\u901a\u3058\u3066\u5408\u6cd5\u5927\u9ebb\u696d\u754c\u306b\u8ca2\u732e\u3057\u307e\u3059\u3002",
  "base": "ibc/D805F1DA50D31B96E4282C1D4181EDDFB1A44A598BFF5666F4B43E4B8BEA95A5"
}
