{
  "localization": "en",
  "name": "Racoon",
  "symbol": "RAC",
  "description": {
    "en": "RAC",
    "de": "RAC",
    "es": "RAC",
    "fa": "RAC",
    "fr": "CAR",
    "gu": "\u0a86\u0ab0\u0a8f\u0ab8\u0ac0",
    "hi": "\u0906\u0930\u090f\u0938\u0940",
    "ja": "RAC",
    "ko": "RAC",
    "pl": "RAK",
    "pt-br": "RAC",
    "ro": "RAC",
    "ru": "\u0420\u0410\u041a",
    "tr": "RAC",
    "zh-cn": "RAC",
    "zh-hk": "RAC",
    "zh-tw": "RAC"
  },
  "coingeckoID": "racoon",
  "base": "ibc/DDF1CD4CDC14AE2D6A3060193624605FF12DEE71CF1F8C19EEF35E9447653493"
}
