{
  "localization": "pl",
  "name": "Yield GATA",
  "symbol": "YGATA",
  "coingeckoID": "yield-gata",
  "websiteURL": "https://gatahub.zone",
  "twitterURL": "https://x.com/GataHubZone",
  "description": "GATA Yield DAO Governance Token obs\u0142ugiwany przez OmniFlixHub<inlang-LineFeed>\nGATA Yield DAO to zdecentralizowana, zarz\u0105dzana przez spo\u0142eczno\u015b\u0107 organizacja, kt\u00f3rej celem jest zr\u00f3wnowa\u017cone generowanie zysk\u00f3w i alokacja zasob\u00f3w. Zarz\u0105dzana przez staker\u00f3w YGATA, GATA Yield DAO jest zaanga\u017cowana w d\u0142ugoterminowy wzrost warto\u015bci i wspieranie projekt\u00f3w zgodnych z Cosmos/IBC, a decyzje podejmowane s\u0105 poprzez otwarte i weryfikowalne zarz\u0105dzanie. Zaprojektowana z my\u015bl\u0105 o r\u00f3wnym udziale, GATA Yield DAO stawia na pierwszym miejscu korzy\u015bci spo\u0142eczno\u015bci i stabilno\u015b\u0107 finansow\u0105.",
  "base": "ibc/50F886EFA15E1FF3D9226B177083A1EFF944176181C70B6131D74FE5AFB1F2C0"
}
