{
  "description": {
    "de": "Der SGD-Stablecoin von Terra Classic.",
    "en": "The SGD stablecoin of Terra Classic.",
    "es": "La moneda estable SGD de Terra Classic.",
    "fa": "استیبل کوین SGD ترا کلاسیک.",
    "fr": "Le stablecoin SGD de Terra Classic.",
    "gu": "ટેરા ક્લાસિકનો SGD સ્ટેબલકોઈન.",
    "hi": "टेरा क्लासिक का SGD स्थिर सिक्का।",
    "ja": "Terra Classic の SGD ステーブルコイン。",
    "ko": "Terra Classic의 SGD 스테이블코인.",
    "pl": "Stabilna moneta SGD Terra Classic.",
    "pt-br": "A stablecoin em SGD da Terra Classic.",
    "ro": "Moneda stabilă SGD a Terra Classic.",
    "ru": "Стейблкоин SGD от Terra Classic.",
    "tr": "Terra Classic'in SGD'lik stablecoin'i.",
    "zh-cn": "Terra Classic 的新加坡元稳定币。",
    "zh-hk": "Terra Classic 的新加坡元穩定幣。",
    "zh-tw": "Terra Classic 的新加坡元穩定幣。"
  },
  "base": "ibc/2FB96E4667FBBE51C86E534017E6787F5B15377AF16815955DC97692CB237208",
  "name": "TerraClassicSGD",
  "symbol": "SGTC"
}