{
  "localization": "fr",
  "name": "Wrapped Lido Staked Ether",
  "symbol": "wstETH",
  "coingeckoID": "wrapped-steth",
  "description": "wstETH est une version envelopp\u00e9e de stETH. Comme certains protocoles DeFi n\u00e9cessitent un m\u00e9canisme d'\u00e9quilibre constant pour les jetons, wstETH maintient votre solde de stETH fixe et utilise un syst\u00e8me de partage sous-jacent pour refl\u00e9ter vos r\u00e9compenses de mise gagn\u00e9es.",
  "base": "ibc/2F21E6D4271DE3F561F20A02CD541DAF7405B1E9CB3B9B07E3C2AC7D8A4338A5"
}
