{
  "description": {
    "de": "Der ELT-Token des Gamma 4 Gaming-Ökosystems von Bluzelle",
    "en": "The ELT token of Bluzelle's Gamma 4 Gaming Ecosystem",
    "es": "El token ELT del ecosistema de juegos Gamma 4 de Bluzelle",
    "fa": "توکن ELT اکوسیستم بازی گاما ۴ بلوزل",
    "fr": "Le jeton ELT de l'écosystème de jeu Gamma 4 de Bluzelle",
    "gu": "બ્લુઝેલના ગામા 4 ગેમિંગ ઇકોસિસ્ટમનું ELT ટોકન",
    "hi": "ब्लूज़ेल के गामा 4 गेमिंग इकोसिस्टम का ELT टोकन",
    "ja": "BluzelleのGamma 4ゲームエコシステムのELTトークン",
    "ko": "Bluzelle의 Gamma 4 Gaming Ecosystem의 ELT 토큰",
    "pl": "Token ELT ekosystemu gier Gamma 4 firmy Bluzelle",
    "pt-br": "O token ELT do Ecossistema de Jogos Gamma 4 da Bluzelle",
    "ro": "Jetonul ELT al ecosistemului de jocuri Gamma 4 al Bluzelle",
    "ru": "Токен ELT игровой экосистемы Gamma 4 от Bluzelle",
    "tr": "Bluzelle'nin Gamma 4 Oyun Ekosisteminin ELT belirteci",
    "zh-cn": "Bluzelle Gamma 4 游戏生态系统的 ELT 代币",
    "zh-hk": "Bluzelle Gamma 4 遊戲生態系統的 ELT 代幣",
    "zh-tw": "Bluzelle Gamma 4 遊戲生態系統的 ELT 代幣"
  },
  "base": "ibc/FDFCC8A906432FA7EFBA430062DA860883F5DDC77B8D64AFA2EE6CD5DC54B6A2",
  "name": "ELT",
  "symbol": "ELT"
}