{
  "description": {
    "de": "Quark ($QUARK) ist der erste erlaubnisfreie CosmWasm-Token, der auf dem Cosmos Hub eingeführt wurde.",
    "en": "Quark ($QUARK) is the first permissionless CosmWasm token launched on the Cosmos Hub.",
    "es": "Quark ($QUARK) es el primer token CosmWasm sin permiso lanzado en Cosmos Hub.",
    "fa": "کوارک (QUARK$) اولین توکن بدون نیاز به مجوز CosmWasm است که در Cosmos Hub راه‌اندازی شده است.",
    "fr": "Quark ($QUARK) est le premier jeton CosmWasm sans autorisation lancé sur le Cosmos Hub.",
    "gu": "ક્વાર્ક ($QUARK) એ કોસ્મોસ હબ પર લોન્ચ કરાયેલું પ્રથમ પરવાનગી વિનાનું CosmWasm ટોકન છે.",
    "hi": "क्वार्क ($QUARK) कॉसमॉस हब पर लॉन्च किया गया पहला अनुमति रहित कॉसमवासम टोकन है।",
    "ja": "Quark（$QUARK）は、Cosmos Hubでリリースされた最初の許可のないCosmWasmトークンです。",
    "ko": "Quark($QUARK)는 Cosmos Hub에서 출시된 최초의 허가 없는 CosmWasm 토큰입니다.",
    "pl": "Quark ($QUARK) to pierwszy nie wymagający zezwoleń token CosmWasm uruchomiony na Cosmos Hub.",
    "pt-br": "Quark ($QUARK) é o primeiro token CosmWasm sem permissão lançado no Cosmos Hub.",
    "ro": "Quark ($QUARK) este primul token CosmWasm fără permisiune lansat pe Cosmos Hub.",
    "ru": "Quark ($QUARK) — первый общедоступный токен CosmWasm, запущенный на Cosmos Hub.",
    "tr": "Quark ($QUARK), Cosmos Hub'da başlatılan ilk izinsiz CosmWasm token'ıdır.",
    "zh-cn": "Quark（$QUARK）是 Cosmos Hub 上推出的第一个无需许可的 CosmWasm 代币。",
    "zh-hk": "Quark（$QUARK）是 Cosmos Hub 上推出的第一個無需許可的 CosmWasm 代幣。",
    "zh-tw": "Quark（$QUARK）是 Cosmos Hub 上推出的第一個無需許可的 CosmWasm 代幣。"
  },
  "base": "ibc/FF7C4EF2AA2132F94D5724B62F05D7458E3F4763F91F05591816D7465FD608E3",
  "name": "Quark",
  "symbol": "QUARK"
}