{
  "description": {
    "de": "Minerva war eine der Hauptgöttinnen, die von den römischen Heiden verehrt wurden, und ist eine Göttin der römischen Mythologie.",
    "en": "Minerva was one of the main goddesses worshiped by the Roman Pagans and is a goddess from Roman Mythology.",
    "es": "Minerva fue una de las principales diosas veneradas por los paganos romanos y es una diosa de la mitología romana.",
    "fa": "مینروا یکی از الهه‌های اصلی مورد پرستش بت‌پرستان رومی و الهه‌ای از اساطیر رومی است.",
    "fr": "Minerve était l'une des principales déesses vénérées par les païens romains et est une déesse de la mythologie romaine.",
    "gu": "મિનર્વા રોમન મૂર્તિપૂજકો દ્વારા પૂજાતી મુખ્ય દેવીઓમાંની એક હતી અને તે રોમન પૌરાણિક કથાઓમાંથી એક દેવી છે.",
    "hi": "मिनर्वा रोमन मूर्तिपूजकों द्वारा पूजी जाने वाली प्रमुख देवियों में से एक थी और वह रोमन पौराणिक कथाओं की देवी हैं।",
    "ja": "ミネルヴァはローマの異教徒が崇拝していた主要な女神の一人であり、ローマ神話に登場する女神である。",
    "ko": "미네르바는 로마 이교도들이 숭배했던 주요 여신 중 하나이며, 로마 신화에 등장하는 여신입니다.",
    "pl": "Minerwa była jedną z głównych bogiń czczonych przez rzymskich pogan. Jest boginią z mitologii rzymskiej.",
    "pt-br": "Minerva era uma das principais deusas adoradas pelos pagãos romanos e é uma deusa da mitologia romana.",
    "ro": "Minerva a fost una dintre principalele zeițe venerate de păgânii romani și este o zeiță din mitologia romană.",
    "ru": "Минерва была одной из главных богинь, которым поклонялись римские язычники, и является богиней из римской мифологии.",
    "tr": "Minerva, Romalı paganların taptığı başlıca tanrıçalardan biriydi ve Roma mitolojisinden bir tanrıçadır.",
    "zh-cn": "米涅瓦是罗马异教徒崇拜的主要女神之一，也是罗马神话中的女神。",
    "zh-hk": "米涅瓦是羅馬異教徒崇拜的主要女神之一，也是羅馬神話中的女神。",
    "zh-tw": "米涅瓦是羅馬異教徒崇拜的主要女神之一，也是羅馬神話中的女神。"
  },
  "base": "ibc/9E1F8DBB64753CAB022F2BDEA0D2C3B53522F372140DDF494AEE94C3078925E8",
  "name": "MINERVA",
  "symbol": "MRVA"
}