{
  "localization": "en",
  "name": "FIRMACHAIN",
  "symbol": "FCT",
  "coingeckoID": "firmachain",
  "description": {
    "en": "FIRMACHAIN adds a signing and verifying e-contract function to the blockchain. Unlocking new limits of electronic contracts with blockchain technology, FIRMACHAIN seeks to resolve all the social and legal issues (contracts, notarial, etc.) with written contracts through the use of electronic contracts based on FIRMACHAIN\u2019s data blockchain.",
    "de": "FIRMACHAIN f\u00fcgt der Blockchain eine Funktion zum Unterzeichnen und Verifizieren von elektronischen Vertr\u00e4gen hinzu. FIRMACHAIN setzt mit der Blockchain-Technologie neue Grenzen f\u00fcr elektronische Vertr\u00e4ge und versucht, alle sozialen und rechtlichen Probleme (Vertr\u00e4ge, Notariat usw.) bei schriftlichen Vertr\u00e4gen durch die Verwendung elektronischer Vertr\u00e4ge auf Grundlage der Daten-Blockchain von FIRMACHAIN zu l\u00f6sen.",
    "es": "FIRMACHAIN agrega una funci\u00f3n de firma y verificaci\u00f3n de contrato electr\u00f3nico a la cadena de bloques. Liberando nuevos l\u00edmites de los contratos electr\u00f3nicos con tecnolog\u00eda blockchain, FIRMACHAIN busca resolver todas las cuestiones sociales y legales (contratos, notariales, etc.) con contratos escritos mediante el uso de contratos electr\u00f3nicos basados en la blockchain de datos de FIRMACHAIN.",
    "fa": "FIRMACHAIN \u06cc\u06a9 \u0639\u0645\u0644\u06a9\u0631\u062f \u0642\u0631\u0627\u0631\u062f\u0627\u062f \u0627\u0644\u06a9\u062a\u0631\u0648\u0646\u06cc\u06a9\u06cc \u0627\u0645\u0636\u0627 \u0648 \u062a\u0623\u06cc\u06cc\u062f \u0631\u0627 \u0628\u0647 \u0628\u0644\u0627\u06a9 \u0686\u06cc\u0646 \u0627\u0636\u0627\u0641\u0647 \u0645\u06cc \u06a9\u0646\u062f. FIRMACHAIN \u0628\u0627 \u0628\u0627\u0632 \u06a9\u0631\u062f\u0646 \u0645\u062d\u062f\u0648\u062f\u06cc\u062a \u0647\u0627\u06cc \u062c\u062f\u06cc\u062f \u0642\u0631\u0627\u0631\u062f\u0627\u062f\u0647\u0627\u06cc \u0627\u0644\u06a9\u062a\u0631\u0648\u0646\u06cc\u06a9\u06cc \u0628\u0627 \u0641\u0646\u0627\u0648\u0631\u06cc \u0628\u0644\u0627\u06a9 \u0686\u06cc\u0646\u060c \u0628\u0647 \u062f\u0646\u0628\u0627\u0644 \u062d\u0644 \u0648 \u0641\u0635\u0644 \u0647\u0645\u0647 \u0645\u0633\u0627\u0626\u0644 \u0627\u062c\u062a\u0645\u0627\u0639\u06cc \u0648 \u062d\u0642\u0648\u0642\u06cc (\u0642\u0631\u0627\u0631\u062f\u0627\u062f\u0647\u0627\u060c \u0627\u0633\u0646\u0627\u062f \u0631\u0633\u0645\u06cc \u0648 \u063a\u06cc\u0631\u0647) \u0628\u0627 \u0642\u0631\u0627\u0631\u062f\u0627\u062f\u0647\u0627\u06cc \u0645\u06a9\u062a\u0648\u0628 \u0627\u0632 \u0637\u0631\u06cc\u0642 \u0627\u0633\u062a\u0641\u0627\u062f\u0647 \u0627\u0632 \u0642\u0631\u0627\u0631\u062f\u0627\u062f\u0647\u0627\u06cc \u0627\u0644\u06a9\u062a\u0631\u0648\u0646\u06cc\u06a9\u06cc \u0645\u0628\u062a\u0646\u06cc \u0628\u0631 \u0628\u0644\u0627\u06a9 \u0686\u06cc\u0646 \u062f\u0627\u062f\u0647 \u0647\u0627\u06cc FIRMACHAIN \u0627\u0633\u062a.",
    "fr": "FIRMACHAIN ajoute une fonction de signature et de v\u00e9rification de contrat \u00e9lectronique \u00e0 la blockchain. Lib\u00e9rant les nouvelles limites des contrats \u00e9lectroniques gr\u00e2ce \u00e0 la technologie blockchain, FIRMACHAIN cherche \u00e0 r\u00e9soudre tous les probl\u00e8mes sociaux et juridiques (contrats, notari\u00e9s, etc.) avec des contrats \u00e9crits gr\u00e2ce \u00e0 l'utilisation de contrats \u00e9lectroniques bas\u00e9s sur la blockchain de donn\u00e9es de FIRMACHAIN.",
    "gu": "FIRMACHAIN \u0aac\u0acd\u0ab2\u0acb\u0a95\u0a9a\u0ac7\u0aa8\u0aae\u0abe\u0a82 \u0ab8\u0ab9\u0ac0 \u0a85\u0aa8\u0ac7 \u0a9a\u0a95\u0abe\u0ab8\u0aa3\u0ac0 \u0a88-\u0a95\u0acb\u0aa8\u0acd\u0a9f\u0acd\u0ab0\u0abe\u0a95\u0acd\u0a9f \u0aab\u0a82\u0a95\u0acd\u0ab6\u0aa8 \u0a89\u0aae\u0ac7\u0ab0\u0ac7 \u0a9b\u0ac7. \u0aac\u0acd\u0ab2\u0acb\u0a95\u0a9a\u0ac7\u0aa8 \u0a9f\u0ac7\u0a95\u0acd\u0aa8\u0acb\u0ab2\u0acb\u0a9c\u0ac0 \u0ab8\u0abe\u0aa5\u0ac7 \u0a88\u0ab2\u0ac7\u0a95\u0acd\u0a9f\u0acd\u0ab0\u0acb\u0aa8\u0abf\u0a95 \u0a95\u0acb\u0aa8\u0acd\u0a9f\u0acd\u0ab0\u0abe\u0a95\u0acd\u0a9f\u0aa8\u0ac0 \u0aa8\u0ab5\u0ac0 \u0aae\u0ab0\u0acd\u0aaf\u0abe\u0aa6\u0abe\u0a93\u0aa8\u0ac7 \u0a85\u0aa8\u0ab2\u0acb\u0a95 \u0a95\u0ab0\u0ac0\u0aa8\u0ac7, FIRMACHAIN FIRMACHAIN \u0aa8\u0abe \u0aa1\u0ac7\u0a9f\u0abe \u0aac\u0acd\u0ab2\u0acb\u0a95\u0a9a\u0ac7\u0aa8 \u0aaa\u0ab0 \u0a86\u0aa7\u0abe\u0ab0\u0abf\u0aa4 \u0a88\u0ab2\u0ac7\u0a95\u0acd\u0a9f\u0acd\u0ab0\u0acb\u0aa8\u0abf\u0a95 \u0a95\u0acb\u0aa8\u0acd\u0a9f\u0acd\u0ab0\u0abe\u0a95\u0acd\u0a9f\u0aa8\u0abe \u0a89\u0aaa\u0aaf\u0acb\u0a97 \u0aa6\u0acd\u0ab5\u0abe\u0ab0\u0abe \u0ab2\u0ac7\u0a96\u0abf\u0aa4 \u0a95\u0ab0\u0abe\u0ab0\u0acb \u0ab8\u0abe\u0aa5\u0ac7 \u0aa4\u0aae\u0abe\u0aae \u0ab8\u0abe\u0aae\u0abe\u0a9c\u0abf\u0a95 \u0a85\u0aa8\u0ac7 \u0a95\u0abe\u0aa8\u0ac2\u0aa8\u0ac0 \u0aae\u0ac1\u0aa6\u0acd\u0aa6\u0abe\u0a93 (\u0a95\u0ab0\u0abe\u0ab0, \u0aa8\u0acb\u0a9f\u0ab0\u0ac0\u0aaf\u0ab2, \u0ab5\u0a97\u0ac7\u0ab0\u0ac7) \u0a89\u0a95\u0ac7\u0ab2\u0ab5\u0abe \u0aae\u0abe\u0a82\u0a97\u0ac7 \u0a9b\u0ac7.",
    "hi": "FIRMACHAIN \u092c\u094d\u0932\u0949\u0915\u091a\u0947\u0928 \u092e\u0947\u0902 \u090f\u0915 \u0939\u0938\u094d\u0924\u093e\u0915\u094d\u0937\u0930 \u0914\u0930 \u0938\u0924\u094d\u092f\u093e\u092a\u0928 \u0908-\u0905\u0928\u0941\u092c\u0902\u0927 \u092b\u093c\u0902\u0915\u094d\u0936\u0928 \u091c\u094b\u0921\u093c\u0924\u093e \u0939\u0948\u0964 \u092c\u094d\u0932\u0949\u0915\u091a\u0947\u0928 \u092a\u094d\u0930\u094c\u0926\u094d\u092f\u094b\u0917\u093f\u0915\u0940 \u0915\u0947 \u0938\u093e\u0925 \u0907\u0932\u0947\u0915\u094d\u091f\u094d\u0930\u0949\u0928\u093f\u0915 \u0905\u0928\u0941\u092c\u0902\u0927\u094b\u0902 \u0915\u0940 \u0928\u0908 \u0938\u0940\u092e\u093e\u0913\u0902 \u0915\u094b \u0905\u0928\u0932\u0949\u0915 \u0915\u0930\u0924\u0947 \u0939\u0941\u090f, FIRMACHAIN FIRMACHAIN \u0915\u0947 \u0921\u0947\u091f\u093e \u092c\u094d\u0932\u0949\u0915\u091a\u0947\u0928 \u092a\u0930 \u0906\u0927\u093e\u0930\u093f\u0924 \u0907\u0932\u0947\u0915\u094d\u091f\u094d\u0930\u0949\u0928\u093f\u0915 \u0905\u0928\u0941\u092c\u0902\u0927\u094b\u0902 \u0915\u0947 \u0909\u092a\u092f\u094b\u0917 \u0915\u0947 \u092e\u093e\u0927\u094d\u092f\u092e \u0938\u0947 \u0932\u093f\u0916\u093f\u0924 \u0905\u0928\u0941\u092c\u0902\u0927\u094b\u0902 \u0915\u0947 \u0938\u093e\u0925 \u0938\u092d\u0940 \u0938\u093e\u092e\u093e\u091c\u093f\u0915 \u0914\u0930 \u0915\u093e\u0928\u0942\u0928\u0940 \u092e\u0941\u0926\u094d\u0926\u094b\u0902 (\u0905\u0928\u0941\u092c\u0902\u0927, \u0928\u094b\u091f\u0930\u0940, \u0906\u0926\u093f) \u0915\u094b \u0939\u0932 \u0915\u0930\u0928\u093e \u091a\u093e\u0939\u0924\u093e \u0939\u0948\u0964",
    "ja": "FIRMACHAIN \u306f\u3001\u30d6\u30ed\u30c3\u30af\u30c1\u30a7\u30fc\u30f3\u306b\u96fb\u5b50\u5951\u7d04\u306e\u7f72\u540d\u3068\u691c\u8a3c\u6a5f\u80fd\u3092\u8ffd\u52a0\u3057\u307e\u3059\u3002\u30d6\u30ed\u30c3\u30af\u30c1\u30a7\u30fc\u30f3\u6280\u8853\u3067\u96fb\u5b50\u5951\u7d04\u306e\u65b0\u305f\u306a\u9650\u754c\u3092\u89e3\u304d\u653e\u3061\u3001FIRMACHAIN \u306f\u3001FIRMACHAIN \u306e\u30c7\u30fc\u30bf \u30d6\u30ed\u30c3\u30af\u30c1\u30a7\u30fc\u30f3\u306b\u57fa\u3065\u304f\u96fb\u5b50\u5951\u7d04\u306e\u4f7f\u7528\u3092\u901a\u3058\u3066\u3001\u66f8\u9762\u306b\u3088\u308b\u5951\u7d04\u306b\u4f34\u3046\u3059\u3079\u3066\u306e\u793e\u4f1a\u7684\u304a\u3088\u3073\u6cd5\u7684\u554f\u984c (\u5951\u7d04\u3001\u516c\u8a3c\u306a\u3069) \u306e\u89e3\u6c7a\u3092\u76ee\u6307\u3057\u307e\u3059\u3002",
    "ko": "FIRMACHAIN\uc740 \ube14\ub85d\uccb4\uc778\uc5d0 \uc804\uc790\uacc4\uc57d \uc11c\uba85 \ubc0f \uac80\uc99d \uae30\ub2a5\uc744 \ucd94\uac00\ud569\ub2c8\ub2e4. FIRMACHAIN\uc740 \ube14\ub85d\uccb4\uc778 \uae30\uc220\uc744 \ud1b5\ud574 \uc804\uc790 \uacc4\uc57d\uc758 \uc0c8\ub85c\uc6b4 \ud55c\uacc4\ub97c \uac1c\ucc99\ud558\uace0, FIRMACHAIN\uc758 \ub370\uc774\ud130 \ube14\ub85d\uccb4\uc778\uc744 \uae30\ubc18\uc73c\ub85c \ud55c \uc804\uc790 \uacc4\uc57d\uc744 \ud1b5\ud574 \uc11c\uba74 \uacc4\uc57d\uc73c\ub85c \ubc1c\uc0dd\ud558\ub294 \ubaa8\ub4e0 \uc0ac\ud68c\uc801, \ubc95\uc801 \ubb38\uc81c(\uacc4\uc57d, \uacf5\uc99d \ub4f1)\ub97c \ud574\uacb0\ud558\uace0\uc790 \ud569\ub2c8\ub2e4.",
    "pl": "FIRMACHAIN dodaje do blockchaina funkcj\u0119 podpisywania i weryfikacji e-umowy. Odblokowuj\u0105c nowe ograniczenia um\u00f3w elektronicznych za pomoc\u0105 technologii blockchain, FIRMACHAIN stara si\u0119 rozwi\u0105za\u0107 wszystkie problemy spo\u0142eczne i prawne (umowy, notarialne itp.) w przypadku um\u00f3w pisemnych poprzez wykorzystanie um\u00f3w elektronicznych opartych na blockchain danych FIRMACHAIN.",
    "pt-br": "FIRMACHAIN adiciona uma fun\u00e7\u00e3o de assinatura e verifica\u00e7\u00e3o de contrato eletr\u00f4nico ao blockchain. Desbloqueando novos limites dos contratos eletr\u00f3nicos com a tecnologia blockchain, a FIRMACHAIN procura resolver todas as quest\u00f5es sociais e jur\u00eddicas (contratos, notariais, etc.) com contratos escritos atrav\u00e9s da utiliza\u00e7\u00e3o de contratos eletr\u00f3nicos baseados na blockchain de dados da FIRMACHAIN.",
    "ro": "FIRMACHAIN adaug\u0103 la blockchain o func\u021bie de semnare \u0219i verificare e-contract. Debloc\u00e2nd noi limite ale contractelor electronice cu tehnologia blockchain, FIRMACHAIN urm\u0103re\u0219te s\u0103 rezolve toate problemele sociale \u0219i juridice (contracte, notariale etc.) cu contracte scrise prin utilizarea contractelor electronice bazate pe data blockchain-ului FIRMACHAIN.",
    "ru": "FIRMACHAIN \u0434\u043e\u0431\u0430\u0432\u043b\u044f\u0435\u0442 \u0432 \u0431\u043b\u043e\u043a\u0447\u0435\u0439\u043d \u0444\u0443\u043d\u043a\u0446\u0438\u044e \u043f\u043e\u0434\u043f\u0438\u0441\u0430\u043d\u0438\u044f \u0438 \u043f\u0440\u043e\u0432\u0435\u0440\u043a\u0438 \u044d\u043b\u0435\u043a\u0442\u0440\u043e\u043d\u043d\u043e\u0433\u043e \u043a\u043e\u043d\u0442\u0440\u0430\u043a\u0442\u0430. \u041e\u0442\u043a\u0440\u044b\u0432\u0430\u044f \u043d\u043e\u0432\u044b\u0435 \u0432\u043e\u0437\u043c\u043e\u0436\u043d\u043e\u0441\u0442\u0438 \u044d\u043b\u0435\u043a\u0442\u0440\u043e\u043d\u043d\u044b\u0445 \u043a\u043e\u043d\u0442\u0440\u0430\u043a\u0442\u043e\u0432 \u0441 \u043f\u043e\u043c\u043e\u0449\u044c\u044e \u0442\u0435\u0445\u043d\u043e\u043b\u043e\u0433\u0438\u0438 \u0431\u043b\u043e\u043a\u0447\u0435\u0439\u043d\u0430, FIRMACHAIN \u0441\u0442\u0440\u0435\u043c\u0438\u0442\u0441\u044f \u0440\u0435\u0448\u0438\u0442\u044c \u0432\u0441\u0435 \u0441\u043e\u0446\u0438\u0430\u043b\u044c\u043d\u044b\u0435 \u0438 \u044e\u0440\u0438\u0434\u0438\u0447\u0435\u0441\u043a\u0438\u0435 \u0432\u043e\u043f\u0440\u043e\u0441\u044b (\u043a\u043e\u043d\u0442\u0440\u0430\u043a\u0442\u044b, \u043d\u043e\u0442\u0430\u0440\u0438\u0430\u043b\u044c\u043d\u044b\u0435 \u0438 \u0442.\u00a0\u0434.) \u0441 \u043f\u043e\u043c\u043e\u0449\u044c\u044e \u043f\u0438\u0441\u044c\u043c\u0435\u043d\u043d\u044b\u0445 \u043a\u043e\u043d\u0442\u0440\u0430\u043a\u0442\u043e\u0432 \u043f\u043e\u0441\u0440\u0435\u0434\u0441\u0442\u0432\u043e\u043c \u0438\u0441\u043f\u043e\u043b\u044c\u0437\u043e\u0432\u0430\u043d\u0438\u044f \u044d\u043b\u0435\u043a\u0442\u0440\u043e\u043d\u043d\u044b\u0445 \u043a\u043e\u043d\u0442\u0440\u0430\u043a\u0442\u043e\u0432 \u043d\u0430 \u043e\u0441\u043d\u043e\u0432\u0435 \u0431\u043b\u043e\u043a\u0447\u0435\u0439\u043d\u0430 \u0434\u0430\u043d\u043d\u044b\u0445 FIRMACHAIN.",
    "tr": "FIRMACHAIN, blockchain'e bir imzalama ve do\u011frulama e-s\u00f6zle\u015fme i\u015flevi ekler. Blockchain teknolojisi ile elektronik s\u00f6zle\u015fmelerin yeni s\u0131n\u0131rlar\u0131n\u0131 a\u00e7an FIRMACHAIN, FIRMACHAIN'in veri blok zincirine dayanan elektronik s\u00f6zle\u015fmelerin kullan\u0131m\u0131 yoluyla t\u00fcm sosyal ve hukuki sorunlar\u0131 (s\u00f6zle\u015fmeler, noter vb.) yaz\u0131l\u0131 s\u00f6zle\u015fmelerle \u00e7\u00f6zmeyi ama\u00e7lamaktad\u0131r.",
    "zh-cn": "FIRMACHAIN\u5728\u533a\u5757\u94fe\u4e0a\u6dfb\u52a0\u4e86\u7535\u5b50\u5408\u540c\u7684\u7b7e\u7f72\u548c\u9a8c\u8bc1\u529f\u80fd\uff0c\u5229\u7528\u533a\u5757\u94fe\u6280\u672f\u89e3\u9501\u7535\u5b50\u5408\u540c\u7684\u65b0\u6781\u9650\uff0c\u529b\u6c42\u901a\u8fc7\u57fa\u4e8eFIRMACHAIN\u6570\u636e\u533a\u5757\u94fe\u7684\u7535\u5b50\u5408\u540c\u89e3\u51b3\u6240\u6709\u4e66\u9762\u5408\u540c\u7684\u793e\u4f1a\u548c\u6cd5\u5f8b\u95ee\u9898\uff08\u5408\u540c\u3001\u516c\u8bc1\u7b49\uff09\u3002",
    "zh-hk": "FIRMACHAIN\u5728\u5340\u584a\u93c8\u4e0a\u589e\u52a0\u4e86\u96fb\u5b50\u5408\u7d04\u7684\u7c3d\u7f72\u548c\u9a57\u8b49\u529f\u80fd\u3002\u5229\u7528\u5340\u584a\u93c8\u6280\u8853\u89e3\u9396\u96fb\u5b50\u5408\u7d04\u7684\u65b0\u9650\u5236\uff0cFIRMACHAIN\u529b\u6c42\u900f\u904e\u4f7f\u7528\u57fa\u65bcFIRMACHAIN\u6578\u64da\u5340\u584a\u93c8\u7684\u96fb\u5b50\u5408\u540c\uff0c\u89e3\u6c7a\u6240\u6709\u66f8\u9762\u5408\u7d04\u7684\u793e\u6703\u548c\u6cd5\u5f8b\u554f\u984c\uff08\u5408\u7d04\u3001\u516c\u8b49\u7b49\uff09\u3002",
    "zh-tw": "FIRMACHAIN\u5728\u5340\u584a\u93c8\u4e0a\u589e\u52a0\u4e86\u96fb\u5b50\u5408\u7d04\u7684\u7c3d\u7f72\u548c\u9a57\u8b49\u529f\u80fd\u3002\u5229\u7528\u5340\u584a\u93c8\u6280\u8853\u89e3\u9396\u96fb\u5b50\u5408\u7d04\u7684\u65b0\u9650\u5236\uff0cFIRMACHAIN\u529b\u6c42\u900f\u904e\u4f7f\u7528\u57fa\u65bcFIRMACHAIN\u6578\u64da\u5340\u584a\u93c8\u7684\u96fb\u5b50\u5408\u540c\uff0c\u89e3\u6c7a\u6240\u6709\u66f8\u9762\u5408\u7d04\u7684\u793e\u6703\u548c\u6cd5\u5f8b\u554f\u984c\uff08\u5408\u7d04\u3001\u516c\u8b49\u7b49\uff09\u3002"
  },
  "base": "ibc/E43ABCC7E80E99E4E6E1226AE5695DDE0F83CB5C257CD04D47C36B8B90C1C839"
}
