{
  "localization": "gu",
  "name": "Hope Galaxy",
  "symbol": "HOPE",
  "description": "Hope Galaxy \u0a8f \u0aa4\u0ac7\u0aa8\u0abe \u0aaa\u0acb\u0aa4\u0abe\u0aa8\u0abe \u0aae\u0ac2\u0ab3 \u0a9f\u0acb\u0a95\u0aa8 $HOPE \u0aaa\u0ab0 \u0a86\u0aa7\u0abe\u0ab0\u0abf\u0aa4 NFT \u0a95\u0ab2\u0ac7\u0a95\u0acd\u0ab6\u0aa8 \u0a9b\u0ac7, \u0a9c\u0ac7 \u0a9c\u0ac2\u0aa8\u0acb \u0a9a\u0ac7\u0a87\u0aa8 \u0aaa\u0ab0 cw20 \u0a9f\u0acb\u0a95\u0aa8 \u0a9b\u0ac7.",
  "base": "ibc/C2A2E9CA95DDD4828B75124B5E27B8401C7D8493BC48353D418CBFC04565899B"
}
