{
  "description": {
    "de": "Pryzms LP-Token für den OSMO/USDC-Pool",
    "en": "Pryzm's LP token for OSMO / USDC pool",
    "es": "Token LP de Pryzm para el pool OSMO/USDC",
    "fa": "توکن LP شرکت Pryzm برای استخر OSMO/USDC",
    "fr": "Jeton LP de Pryzm pour le pool OSMO/USDC",
    "gu": "OSMO / USDC પૂલ માટે Pryzm નું LP ટોકન",
    "hi": "OSMO / USDC पूल के लिए Pryzm का LP टोकन",
    "ja": "OSMO / USDCプール向けのPryzmのLPトークン",
    "ko": "OSMO/USDC 풀을 위한 Pryzm의 LP 토큰",
    "pl": "Token LP firmy Pryzm dla puli OSMO/USDC",
    "pt-br": "Token LP da Pryzm para pool OSMO/USDC",
    "ro": "Tokenul LP al Pryzm pentru pool-ul OSMO / USDC",
    "ru": "Токен LP от Pryzm для пула OSMO/USDC",
    "tr": "Pryzm'in OSMO / USDC havuzu için LP tokeni",
    "zh-cn": "Pryzm 的 LP 代币用于 OSMO / USDC 池",
    "zh-hk": "Pryzm 的 LP 代幣用於 OSMO / USDC 池",
    "zh-tw": "Pryzm 的 LP 代幣用於 OSMO / USDC 池"
  },
  "base": "ibc/3C793E97322DF85D1B337E65EA10712C506E7A02F76F83DB1AC4AB4D99F7B11A",
  "name": "OSMO / USDC LP",
  "symbol": "OSMO-USDC-LP"
}