{
  "localization": "fa",
  "name": "Litecoin (Int3)",
  "symbol": "LTC.int3",
  "websiteURL": "https://litecoin.org/",
  "twitterURL": "https://x.com/litecoin",
  "description": "LTC \u0628\u0648\u0645\u06cc \u0627\u0632 \u0628\u0644\u0627\u06a9\u0686\u06cc\u0646 \u0644\u0627\u06cc\u062a \u06a9\u0648\u06cc\u0646 \u0627\u0632 \u0637\u0631\u06cc\u0642 \u067e\u0644 Int3face \u0645\u062a\u0635\u0644 \u0645\u06cc\u200c\u0634\u0648\u062f",
  "base": "ibc/905326586AE1C86AC8B1CDB20BE957DE5FB23963EDD2C9ADD3E835CC22115A46"
}
