{
  "localization": "pl",
  "name": "POSTHUMAN",
  "symbol": "PHMN",
  "coingeckoID": "posthuman",
  "websiteURL": "https://posthuman.digital/",
  "twitterURL": "https://twitter.com/POSTHUMAN_DVS",
  "description": "Natywny token cw20 dla PHMN na Juno Chain<inlang-LineFeed>\n$PHMN jest tokenem zarz\u0105dzania rozproszonego walidatora. Podobnie jak w przypadku \u0142a\u0144cuch\u00f3w PoS, ka\u017cdy posiadacz posiada prawo g\u0142osu proporcjonalne do liczby zablokowanych token\u00f3w. Posiadacze PHMN mog\u0105 zarz\u0105dza\u0107 walidatorem POSTHUMAN za po\u015brednictwem DAODAO. Przyk\u0142adowo o decyzjach takich jak dywersyfikacja skarbu, aktualizacja stawki prowizji walidatora czy wyj\u015bcie z sieci decyduje spo\u0142eczno\u015b\u0107 PHMN.",
  "base": "ibc/D3B574938631B0A1BA704879020C696E514CFADAA7643CDE4BD5EB010BDE327B"
}
