{
  "localization": "de",
  "name": "Wrapped Lido Staked Ether",
  "symbol": "wstETH",
  "coingeckoID": "wrapped-steth",
  "description": "wstETH ist eine Wrapped-Version von stETH. Da einige DeFi-Protokolle einen konstanten Ausgleichsmechanismus f\u00fcr Token erfordern, h\u00e4lt wstETH Ihren stETH-Saldo konstant und verwendet ein zugrunde liegendes Anteilssystem, um Ihre verdienten Staking-Belohnungen widerzuspiegeln.",
  "base": "ibc/2F21E6D4271DE3F561F20A02CD541DAF7405B1E9CB3B9B07E3C2AC7D8A4338A5"
}
