{
  "localization": "pl",
  "name": "Quicksilver",
  "symbol": "QCK",
  "coingeckoID": "quicksilver",
  "websiteURL": "https://quicksilver.zone/",
  "twitterURL": "https://twitter.com/quicksilverzone",
  "description": "QCK - rodzimy token Quicksilvera<inlang-LineFeed>\nLiquid Staw swoje aktywa Cosmos za pomoc\u0105 preferowanego weryfikatora i otrzymuj aktywa stakowane w formie p\u0142ynnej (qASSET), kt\u00f3rych mo\u017cesz u\u017cywa\u0107 do wymiany, \u0142\u0105czenia, po\u017cyczania i nie tylko, a wszystko to podczas gdy Twoja pierwotna stawka zarabia na stawce APY z zabezpieczenia sieci.",
  "base": "ibc/635CB83EF1DFE598B10A3E90485306FD0D47D34217A4BE5FD9977FA010A5367D"
}
