{
  "localization": "pt-br",
  "name": "Kujira",
  "symbol": "KUJI",
  "coingeckoID": "kujira",
  "websiteURL": "https://kujira.network/",
  "twitterURL": "https://twitter.com/TeamKujira",
  "description": "Kujira \u00e9 uma plataforma de finan\u00e7as descentralizadas (DeFi) que oferece um conjunto de ferramentas e servi\u00e7os para gerenciar e otimizar ativos e investimentos digitais.<inlang-LineFeed>\nKujira fornece uma plataforma DeFi abrangente que inclui ferramentas para empr\u00e9stimos, empr\u00e9stimos e produ\u00e7\u00e3o agr\u00edcola, aproveitando a tecnologia blockchain para oferecer uma experi\u00eancia de usu\u00e1rio transparente, segura e eficiente. O token nativo, KUJI, \u00e9 central para o ecossistema, usado para taxas de transa\u00e7\u00e3o, piquetagem e governan\u00e7a. O design centrado no usu\u00e1rio e os recursos inovadores do Kujira o tornam uma escolha popular no espa\u00e7o DeFi, permitindo aos usu\u00e1rios maximizar seus retornos e gerenciar com efic\u00e1cia seus ativos digitais.",
  "base": "ibc/BB6BCDB515050BAE97516111873CCD7BCF1FD0CCB723CC12F3C4F704D6C646CE"
}
