{
  "description": {
    "de": "Virtuelle (nicht übertragbare) Währung zur Bezahlung von Gas",
    "en": "Virtual(non-transferable) coin used to pay gas",
    "es": "Moneda virtual (no transferible) utilizada para pagar gasolina",
    "fa": "سکه مجازی (غیرقابل انتقال) که برای پرداخت گس استفاده می‌شود",
    "fr": "Monnaie virtuelle (non transférable) utilisée pour payer l'essence",
    "gu": "ગેસ ચૂકવવા માટે વપરાતો વર્ચ્યુઅલ (બિન-તબદીલીપાત્ર) સિક્કો",
    "hi": "गैस का भुगतान करने के लिए इस्तेमाल किया जाने वाला आभासी (गैर-हस्तांतरणीय) सिक्का",
    "ja": "ガス代の支払いに使用される仮想（譲渡不可）コイン",
    "ko": "가스비 지불에 사용되는 가상(양도 불가) 코인",
    "pl": "Wirtualna (nieprzenoszalna) moneta używana do płacenia za gaz",
    "pt-br": "Moeda virtual (intransferível) usada para pagar gasolina.",
    "ro": "Monedă virtuală (netransferabilă) folosită pentru plata benzinei",
    "ru": "Виртуальная (непередаваемая) монета, используемая для оплаты газа",
    "tr": "Gaz ödemelerinde kullanılan sanal (devredilemez) para birimi",
    "zh-cn": "用于支付 Gas 费的虚拟（不可转让）代币",
    "zh-hk": "用於支付 Gas 費的虛擬（不可轉讓）代幣",
    "zh-tw": "用於支付 Gas 費的虛擬（不可轉讓）代幣"
  },
  "base": "ibc/D59DB4C0B161B04CFD4B83E583AB557752EC7C56D4A170FF75A6D1CF1946F603",
  "name": "GAS",
  "symbol": "GAS"
}