{
  "localization": "zh-tw",
  "name": "HOOD",
  "symbol": "HOOD",
  "websiteURL": "https://ffsc.site",
  "twitterURL": "https://x.com/FortunateFewNFT",
  "description": "\u591a\u93c8 NFT \u793e\u7fa4\u5e73\u53f0 The Fortunate Few \u7684\u793e\u7fa4\u4ee3\u5e63\u3002<inlang-LineFeed>\nHOOD \u662f The Fortunate Few \u7684\u793e\u7fa4\u4ee3\u5e63\uff0cThe Fortunate Few \u662f\u4e00\u500b\u591a\u93c8 NFT \u793e\u7fa4\u5e73\u53f0\u548c DAO\uff0c\u5176\u5275\u4e16\u5408\u8f2f\u53ef\u5728 Stargaze \u5e02\u5834\u4e0a\u8cfc\u8cb7\u3002\u8a72\u793e\u5340\u8207\u5176\u4ed6 NFT \u6536\u85cf\u548c\u793e\u5340\u9032\u884c\u4ea4\u4e92\uff0c\u5305\u62ec Hooded Syndicate\u3001Jack-O-Hoods \u548c Hoods of Christmas NFT \u6536\u85cf\u3002\u8a72\u8a08\u756b\u9084\u8207 NFTS \u5408\u4f5c\u63a8\u51fa\u4e86\u300a\u5b87\u5b99\u5ca1\u7403\u6a5f NFT\u300b\u7cfb\u5217\uff0c\u4e26\u8207 Stargaze \u4e0a\u7684\u300a\u72fc\u7375\u4eba\u300b\u9032\u884c\u4e86\u5408\u4f5c\u3002\u52a0\u5165\u300c\u5e78\u904b\u5c11\u6578\u4eba\u300d\u7684\u884c\u5217\uff0c\u4e26\u900f\u904e\u5b98\u65b9 Discord \u983b\u9053\u4e86\u89e3\u66f4\u591a\uff1ahttps://discord.gg/HDRNRTUTXC",
  "base": "ibc/48047CBAA27D0526BA9E6BEC9D77D9B796AA95E35C95891C7F19C3F0D32473F6"
}
