{
  "localization": "fa",
  "name": "Internet Computer",
  "symbol": "ICP",
  "coingeckoID": "internet-computer",
  "websiteURL": "https://internetcomputer.org/",
  "twitterURL": "https://x.com/dfinity",
  "description": "توکن بومی کامپیوتر اینترنتی<inlang-LineFeed>\nبلاک چین کامپیوتر اینترنتی شامل یک تجدید نظر اساسی در طراحی بلاک چین است که با نوآوری در رمزنگاری تقویت شده است. این اولین بلاک چین \"رایانه جهانی\" را ارائه می کند که می تواند برای ساخت تقریباً هر سیستم یا سرویس آنلاین وب 2.0 و خدمات وب 3، از جمله خدمات رسانه های اجتماعی web3، بدون نیاز به فناوری اطلاعات سنتی متمرکز مانند خدمات رایانش ابری استفاده شود. همچنین قراردادهای هوشمندی را که میزبانی می‌کند قادر می‌سازد تا مستقیماً تراکنش‌ها را روی سایر بلاک چین‌ها ایجاد کنند، که به نوبه خود تمرکززدایی کامل سرویس‌های آنلاین و web3 را برای اولین بار ممکن می‌سازد."
}