{
  "localization": "ru",
  "name": "Kujira",
  "symbol": "KUJI",
  "coingeckoID": "kujira",
  "websiteURL": "https://kujira.network/",
  "twitterURL": "https://twitter.com/TeamKujira",
  "description": "Kujira — это платформа децентрализованного финансирования (DeFi), предлагающая набор инструментов и услуг для управления и оптимизации цифровых активов и инвестиций.<inlang-LineFeed>\nKujira предоставляет комплексную платформу DeFi, которая включает в себя инструменты для кредитования, заимствования и получения прибыли, используя технологию блокчейна для обеспечения прозрачного, безопасного и эффективного взаимодействия с пользователем. Собственный токен KUJI занимает центральное место в экосистеме и используется для комиссий за транзакции, размещения ставок и управления. Ориентированный на пользователя дизайн и инновационные функции Kujira делают его популярным выбором в сфере DeFi, позволяя пользователям максимизировать свою прибыль и эффективно управлять своими цифровыми активами."
}