{
  "localization": "pl",
  "name": "Lombard Staked Bitcoin (Lombard Ledger)",
  "symbol": "LBTC.lom",
  "websiteURL": "https://lombard.finance",
  "twitterURL": "https://x.com/Lombard_Finance",
  "description": "LBTC to płynny Bitcoin; jest dochodowy, międzyłańcuchowy i 1:1 zabezpieczony przez BTC. LBTC umożliwia dochodowy BTC przemieszczanie się międzyłańcuchowo bez fragmentacji płynności i jest zaprojektowany tak, aby płynnie zintegrować Bitcoin z ekosystemem zdecentralizowanych finansów (DeFi) przy jednoczesnym zachowaniu bezpieczeństwa i integralności bazowego aktywa."
}