{
  "localization": "zh-hk",
  "name": "MilkyWay",
  "symbol": "MILK",
  "websiteURL": "https://milkyway.zone",
  "twitterURL": "https://x.com/milky_way_zone",
  "description": "MilkyWay 的原生代幣<inlang-LineFeed><inlang-LineFeed>MilkyWay（MILK）是第一個模組化質押門戶，旨在重新定義模組化生態系統內的安全性和可擴展性。作為模組化質押的先驅，MilkyWay 整合了流動性質押和重新質押解決方案，以解決分散的信任問題並增強整個網路的加密經濟安全性。<inlang-LineFeed>\nMilkyWay 於 2023 年 12 月推出，是 Celestia 生態系統的首個流動性質押解決方案，它使用戶能夠解鎖質押的 TIA 部位並參與各種 DeFi 協議。這一初始階段引入了 milkTIA，它已被廣泛採用並成為 TIA 的主要 LST。在此成功的基礎上，MilkyWay 現已進入第二階段：多元資產、多鏈模組化再質押協議。<inlang-LineFeed>\nMilkyWay 的架構是專門為模組化而建造的。與傳統解決方案不同，其模組化設計允許主動驗證服務 (AVS) 透過可程式規則完全定製或「插入」其安全解決方案，包括資產委託和削減機制。透過重新質押原生資產和流動質押資產，使用者可以為 AVS 或任何需要其自身獨特驗證流程進行驗證的鏈下程序和系統提供安全性。這種方法可確保無縫集成，同時最大限度地降低操作複雜性。<inlang-LineFeed><inlang-LineFeed>透過可程式規則，AVS 可以定義資產配置和股權分配，提供以營運商為中心和以 AVS 為中心的模型，以實現更好的控制。削減規則透過可自訂的機制（如權益削減、監獄削減和銷毀削減）進一步增強了安全性，使 AVS 能夠將這些功能與其風險狀況相結合。這些可擴展的功能確保 MilkyWay 隨著其 AVS 合作夥伴的需求而發展，重新定義質押和重新質押，並專注於信任、創新和模組化。"
}