{
  "localization": "ja",
  "name": "Pundi X Token",
  "symbol": "PUNDIX",
  "coingeckoID": "pundi-x-2",
  "websiteURL": "https://pundix.com",
  "twitterURL": "https://x.com/PundiXLabs",
  "description": "PUNDIX トークンは、PundiX Chain や XPOS を含む Pundi X エコシステム内で機能するネイティブ トークンです。<inlang-LineFeed>\nPUNDIX トークンは、PundiX Chain や XPOS を含む Pundi X エコシステム内で機能するネイティブ トークンです。PUNDIX には、次のようないくつかのコア ユース ケースがあります。\n- XPOS を通じて商店から商品やサービスの支払いを受ける<inlang-LineFeed>- PundiXチェーンのガス料金<inlang-LineFeed>- XPOSでのトークンのリスト<inlang-LineFeed>- ロイヤルティプログラムや広告に対する加盟店の支払い"
}