{
  "localization": "de",
  "name": "Pyth Network",
  "symbol": "PYTH",
  "coingeckoID": "pyth-network",
  "description": "Pyth ist ein Protokoll, das es Marktteilnehmern ermöglicht, Preisinformationen on-chain zu veröffentlichen, damit andere sie nutzen können. Das Protokoll ist eine Interaktion zwischen drei Parteien:\n-Herausgeber übermitteln Preisinformationen an das Orakelprogramm von Pyth. Pyth verfügt für jedes Produkt über mehrere Datenherausgeber, um die Genauigkeit und Robustheit des Systems zu verbessern.\n- Das Orakelprogramm von Python kombiniert die Daten der Herausgeber, um einen einzigen Gesamtpreis und ein Konfidenzintervall zu erstellen.\nVerbraucher lesen die vom Orakelprogramm erstellten Preisinformationen.<inlang-LineFeed>\nDas Oracle-Programm von Pyth läuft gleichzeitig sowohl auf dem Solana-Mainnet als auch auf Pythnet. Jede Instanz des Programms ist für ihren eigenen Satz von Preis-Feeds verantwortlich. Solana-Preis-Feeds sind für die Verwendung durch Solana-Protokolle verfügbar. Da das Oracle-Programm selbst auf Solana läuft, stehen die resultierenden Preise in diesem Fall den Verbrauchern sofort zur Verfügung, ohne dass zusätzliche Arbeit erforderlich ist. Pythnet-Preis-Feeds sind auf über 12 Blockchains verfügbar. Die auf Pythnet erstellten Preise werden kettenübergreifend übertragen, um die Verbraucher auf diesen Blockchains zu erreichen.<inlang-LineFeed>\nIn beiden Fällen ist die kritische Komponente des Systems das Oracle-Programm, das die Daten jedes einzelnen Herausgebers kombiniert. Dieses Programm verwaltet eine Reihe verschiedener Solana-Konten, die die Produkte auf Pyth und ihre aktuellen Preisdaten auflisten. Herausgeber veröffentlichen ihren Preis und ihre Konfidenz, indem sie in jedem Slot mit dem Oracle-Programm interagieren. Das Programm speichert diese Informationen in seinen Konten. Das erste Preisupdate in einem Slot löst zusätzlich eine Preisaggregation aus, die die Preisdaten des vorherigen Slots zu einem einzigen Gesamtpreis und Konfidenzintervall kombiniert. Dieser Gesamtpreis wird auf das Solana-Konto geschrieben, wo er von anderen On-Chain-Programmen gelesen und für die Übertragung an andere Blockchains verfügbar ist."
}