{
  "localization": "pl",
  "name": "Tinkernet",
  "symbol": "TNKR",
  "coingeckoID": "tinkernet",
  "websiteURL": "https://tinker.network",
  "twitterURL": "https://twitter.com/TinkerParachain",
  "description": "Natywna opłata, zarządzanie i token stakingowy Tinkernet Parachain.<inlang-LineFeed>\nTinkernet to parachain Kusama i siostrzana sieć InvArch Network na Polkadot. Tinkernet to eksperymentalny poligon doświadczalny, na którym wdrażane i testowane są protokoły zarządzania kontami omnichain i DAO przed wdrożeniem w sieci InvArch. Protokoły w Tinkernet realizują takie funkcje, jak wielołańcuchowe konta multisig i staking DAO. W przeciwieństwie do sieci testowej, Tinkernet oferuje prawdziwą wartość."
}