{
  "localization": "ru",
  "name": "Yield GATA",
  "symbol": "YGATA",
  "coingeckoID": "yield-gata",
  "websiteURL": "https://gatahub.zone",
  "twitterURL": "https://x.com/GataHubZone",
  "description": "Токен управления GATA Yield DAO, работающий на OmniFlixHub<inlang-LineFeed>\nGATA Yield DAO — это децентрализованная, управляемая сообществом организация, ориентированная на устойчивое получение дохода и распределение ресурсов. Управляемая участниками YGATA, GATA Yield DAO стремится к долгосрочному росту стоимости и поддержке согласованных проектов в Cosmos/IBC, при этом решения принимаются посредством открытого и проверяемого управления. GATA Yield DAO, созданная для равноправного участия, ставит во главу угла выгоды для сообщества и финансовую устойчивость."
}